mlpack-4.6.2.dist-info/RECORD
mlpack-4.6.2.dist-info/WHEEL
mlpack-4.6.2.dist-info/top_level.txt
mlpack-4.6.2.dist-info/METADATA
mlpack/linear_svm.cpython-313-darwin.so
mlpack/preprocess_split.cpython-313-darwin.so
mlpack/preprocess_binarize.cpython-313-darwin.so
mlpack/preprocess_scale.cpython-313-darwin.so
mlpack/adaboost.py
mlpack/gmm_generate.cpython-313-darwin.so
mlpack/knn.cpython-313-darwin.so
mlpack/lmnn.cpython-313-darwin.so
mlpack/kmeans.cpython-313-darwin.so
mlpack/adaboost_classify.cpython-313-darwin.so
mlpack/arma_numpy.cpython-313-darwin.so
mlpack/local_coordinate_coding.cpython-313-darwin.so
mlpack/fastmks.cpython-313-darwin.so
mlpack/nbc.cpython-313-darwin.so
mlpack/gmm_probability.cpython-313-darwin.so
mlpack/adaboost_probabilities.cpython-313-darwin.so
mlpack/gmm_train.cpython-313-darwin.so
mlpack/emst.cpython-313-darwin.so
mlpack/matrix_utils.py
mlpack/hmm_train.cpython-313-darwin.so
mlpack/kfn.cpython-313-darwin.so
mlpack/hmm_generate.cpython-313-darwin.so
mlpack/linear_regression_train.cpython-313-darwin.so
mlpack/nca.cpython-313-darwin.so
mlpack/hmm_loglik.cpython-313-darwin.so
mlpack/__init__.py
mlpack/linear_regression_predict.cpython-313-darwin.so
mlpack/sparse_coding.cpython-313-darwin.so
mlpack/hmm_viterbi.cpython-313-darwin.so
mlpack/image_converter.cpython-313-darwin.so
mlpack/pca.cpython-313-darwin.so
mlpack/approx_kfn.cpython-313-darwin.so
mlpack/preprocess_describe.cpython-313-darwin.so
mlpack/perceptron.cpython-313-darwin.so
mlpack/adaboost_train.cpython-313-darwin.so
mlpack/dbscan.cpython-313-darwin.so
mlpack/decision_tree.cpython-313-darwin.so
mlpack/logistic_regression.cpython-313-darwin.so
mlpack/softmax_regression.cpython-313-darwin.so
mlpack/mean_shift.cpython-313-darwin.so
mlpack/nmf.cpython-313-darwin.so
mlpack/preprocess_one_hot_encoding.cpython-313-darwin.so
mlpack/kde.cpython-313-darwin.so
mlpack/lsh.cpython-313-darwin.so
mlpack/hoeffding_tree.cpython-313-darwin.so
mlpack/radical.cpython-313-darwin.so
mlpack/kernel_pca.cpython-313-darwin.so
mlpack/linear_regression.py
mlpack/preprocess_json_params.py
